sysram.py
sysram-1.0.dist-info/WHEEL
sysram-1.0.dist-info/METADATA
sysram-1.0.dist-info/RECORD
